Primavera_REST_Api/__endpointsEnum.py
Primavera_REST_Api/__eppmSession.py
Primavera_REST_Api/__init__.py
Primavera_REST_Api/__method.py
Primavera_REST_Api/__primavera.py
Primavera_REST_Api-0.1.0.dist-info/LICENCE
Primavera_REST_Api-0.1.0.dist-info/METADATA
Primavera_REST_Api-0.1.0.dist-info/WHEEL
Primavera_REST_Api-0.1.0.dist-info/top_level.txt
Primavera_REST_Api-0.1.0.dist-info/RECORD
