Metadata-Version: 2.1
Name: Primavera-REST-Api
Version: 0.1.0
Summary: Primavera EPPM REST API client
Home-page: https://github.com/EnverMT/Primavera_REST_API
Author: EnverMT
Author-email: anvarmtg@gmail.com
License: MIT
Keywords: primavera,rest,api
Classifier: Programming Language :: Python :: 3
Classifier: License :: OSI Approved :: MIT License
Classifier: Operating System :: OS Independent
License-File: LICENCE
Requires-Dist: requests
